{
    "1": {
        "page": 323,
        "mark": "!",
        "la": "Memoria sancti [1|Bonifatii], ..."
    },

    "2": {
        "la": "..."
    },

    "3": {
        "la": "..."
    },

    "4": {
        "la": "..."
    },

    "5": {
        "mark": "*",
        "la": "..."
    },

    "6": {
        "page": 324,
        "la": "Docci apud Frisios, sanctorum [1|Eobani], episcopi, [2|Adelarii] et novem sociorum*, martyrum, ... sunt.[/][/]*Quorum nomina: sancti [todo-3|Vintrungus] et [todo-4|Gualterius], presbyteri; [todo-5|Amundus], [todo-6|Sevibaldus] et [todo-7|Bosa], diaconi; [todo-8|Vaccarus], [todo-9|Gundecarus], [todo-10|Ellurus] et [todo-11|Atevulfus], monachi."
    },

    "7": {
        "la": "..."
    },

    "8": {
        "mark": "*",
        "la": "..."
    },

    "9": {
        "mark": "*",
        "la": "..."
    },

    "10": {
        "la": "..."
    },

    "11": {
        "la": "..."
    }
}
