{
    "1": {
        "page": 235,
        "la": "I[color:red]N monte Thabor [1|Transfiguratio Domini nostri Iesu Christi].[:color]"
    },

    "2": {
        "la": "Romae via Appia in coemeterio Callisti natalis beati [1|Xysti secundi] Papae et martyris, ..."
    },

    "3": {
        "la": "Item sanctorum martyrum [1|Felicissimi] et [2|Agapiti] eiusdem beati Xysti diaconorum, [3|Ianuarij], [4|Magni], [5|Innocentij], et [6|Stephani] subdiaconorum, qui ... cum eis beatus [7|Quartus], ut ..."
    },

    "4": {
        "la": "..."
    },

    "5": {
        "page": 236,
        "la": "Romae sancti [1|Hormisdae] Papae et confessoris."
    },

    "6": {
        "la": "..."
    }
}
