{
    "names": {
        "pl": "Łucja"
    },
    "translations": {
        "la": [
            "Lucia"
        ],
        "en": [
            "Lucia"
        ],
        "pl": [
            "Łucja"
        ],
        "it": [
            "Lucia"
        ]
    },
    "links": {
        "records/patrons/lucia/fil": {
            "it": "Lucia Filippini",
            "la": "Lucia Filippini",
            "en": "Lucy Filippini",
            "pl": "Łucja Filippini"
        },
        "records/patrons/lucia/syr": {
            "it": "Lucia da Siracusa",
            "la": "Lucia Syracusana",
            "en": "Lucia of Syracuse",
            "pl": "Łucja z Syrakuz"
        },
        "records/patrons/margarita/sze": {
            "pl": "Małgorzata Łucja Szewczyk",
            "en": "Margaret Lucy Szewczyk",
            "la": "Margarita Lucia Szewczyk"
        }
    }
}