{
    "names": {
        "la": "Anscharius"
    },
    "translations": {
        "la": [
            "Ansgarius",
            "Anscharius"
        ],
        "en": [
            "Ansgar",
            "Oscar"
        ],
        "pl": [
            "Ansgar",
            "Oskar"
        ],
        "de": [
            "Ansgar",
            "Anskar"
        ],
        "es": [
            "Óscar"
        ]
    },
    "links": [
        "records/patrons/ansgarius/ham",
        "records/patrons/ansgarius/rom"
    ]
}