{
    "names": {
        "el": "Διονύσιος",
        "grc": "Διονύσιος"
    },
    "translations": {
        "la": [
            "Dionysius"
        ],
        "en": [
            "Denis"
        ],
        "pl": [
            "Dionizy"
        ],
        "el": [
            "Διονύσιος"
        ],
        "fr": [
            "Denis"
        ],
        "it": [
            "Dionigi"
        ],
        "grc": [
            "Διονύσιος"
        ]
    },
    "links": [
        "records/patrons/dionysius/1pp",
        "records/patrons/dionysius/1pp",
        "records/patrons/dionysius/aqu",
        "records/patrons/dionysius/aqu",
        "records/patrons/dionysius/are",
        "records/patrons/dionysius/are",
        "records/patrons/dionysius/cor",
        "records/patrons/dionysius/cor",
        "records/patrons/dionysius/lut",
        "records/patrons/dionysius/lut"
    ]
}