{
    "names": {
        "la": "Đình",
        "en": "Đình",
        "pl": "Đình",
        "vi": "Đình"
    },
    "translations": {
        "la": [
            "Đình"
        ],
        "en": [
            "Đình"
        ],
        "pl": [
            "Đình"
        ],
        "vi": [
            "Đình"
        ]
    },
    "links": [
        "records/patrons/iosephus/ngu",
        "records/patrons/iosephus/ngu",
        "records/patrons/iosephus/ngu",
        "records/patrons/iosephus/ngu"
    ]
}