{
    "names": {
        "la": "Simeon",
        "en": "Simeon"
    },
    "translations": {
        "la": [
            "Simeon",
            "Symeon"
        ],
        "en": [
            "Simeon"
        ],
        "pl": [
            "Symeon"
        ]
    },
    "links": [
        "records/patrons/simeon/sen",
        "records/patrons/simeon/sen",
        "records/patrons/simeon/sta",
        "records/patrons/simeon/sta",
        "records/patrons/simeon/sti",
        "records/patrons/simeon/sti"
    ]
}