{
    "names": {
        "en": [
            "John Adams"
        ],
        "la": [
            "Ioannes Adams"
        ],
        "pl": [
            "Jan Adams"
        ]
    },
    "forenames": ["ioannes"],
    "surnames": [
        {
            "en": "Adams"
        }
    ],
    "epithets": null,

    "active": true,

    "born": ["~1543"],
    "died": ["1586-10-08"],
    "beatified": {
        "type": "ceremonially",
        "date": "1987-11-22"
    },
    "canonized": null,
    "anniversary": ["05-04"],

    "categories": ["vir", "martyr", "presbyter"],

    "data-links": {
        "mr-1584": [],
        "mr-1584-movable": [],

        "mr-1956": [],
        "mr-1956-movable": [],

        "mr-2004": ["1:oct./8#7"],
        "mr-2004-movable": []
    },

    "sources": {
        "causesanti": "https://www.causesanti.va/it/santi-e-beati/85-martiri-inglesi.html",
        "gcatholic": "https://gcatholic.org/p/66872",
        "wiki": [
            "https://en.wikipedia.org/wiki/John_Adams_(Catholic_martyr)",
            "https://pl.wikipedia.org/wiki/Osiemdziesi%C4%99ciu_pi%C4%99ciu_m%C4%99czennik%C3%B3w_Anglii_i_Walii"
        ]
    }
}
