{
    "flu": {
        "de": "Niklaus von Flüe",
        "la": "Nicolaus de Flüe",
        "en": "Nicholas of Flüe",
        "pl": "Mikołaj z Flüe"
    },
    "ges": {
        "it": "Nicola da Gesturi",
        "la": "Nicolaus de Gesturi",
        "en": "Nicholas of Gesturi",
        "pl": "Mikołaj z Gesturi"
    },
    "myr": {
        "el": "Νικόλαος",
        "la": "Nicolaus Myrensis",
        "en": "Nicholas of Myra",
        "pl": "Mikołaj z Miry"
    },
    "stu": {
        "la": "Nicolaus Studita",
        "en": "Nicholas the Studite",
        "pl": "Mikołaj Studita",
        "fr": "Nicolas le Studite"
    }
}