{
    "names": {
        "la": [
            "Aquilinus de Scillium",
            "Acyllinus de Scillium"
        ],
        "en": [
            "Aquilinus of Scillium",
            "Acyllinus of Scillium"
        ],
        "pl": [
            "Akwilin ze Scilium",
            "Acylin ze Scilium"
        ]
    },
    "forenames": ["aquilinus"],
    "surnames": null,
    "epithets": null,

    "active": true,

    "born": null,
    "died": ["180-07-17"],
    "beatified": null,
    "canonized": null,
    "anniversary": null,

    "categories": ["vir", "martyr"],

    "data-links": {
        "mr-1584": ["6:Iul./17#2"],
        "mr-1584-movable": [],

        "mr-1956": ["6:Julii/17#2"],
        "mr-1956-movable": [],

        "mr-2004": ["6:iul./17#1"],
        "mr-2004-movable": []
    },

    "feasts": {
        "tms": {
            "data-links": {
                "mr-1584": ["18:Iul./17#2"],
                "mr-1584-movable": [],

                "mr-1956": [],
                "mr-1956-movable": [],

                "mr-2004": [],
                "mr-2004-movable": []
            }
        }
    },

    "sources": {
        "causesanti": null,
        "gcatholic": "https://gcatholic.org/p/73675",
        "wiki": "https://en.wikipedia.org/wiki/Scillitan_Martyrs"
    }
}
