{
    "1": {
        "page": 113,
        "la": "Natalis beatorum [1|Philippi] et [2|Jacobi] Apostolorum. ..."
    },

    "2": {
        "la": "..."
    },

    "3": {
        "la": "..."
    },

    "4": {
        "la": "..."
    },

    "5": {
        "la": "..."
    },

    "6": {
        "la": "..."
    },

    "7": {
        "la": "..."
    },

    "8": {
        "la": "..."
    },

    "9": {
        "page": 114,
        "la": "..."
    },

    "10": {
        "la": "Neapoli, in Campania, sancti [1|Francisci de Hieronymo], ..., Sacerdotis ... et Confessoris, ..."
    },

    "11": {
        "la": "..."
    },

    "12": {
        "la": "Carali, in Sardinia, sancti [1|Ignatii a Laconi], ..."
    }
}
