{
    "1": {
        "page": 627,
        "mark": "!",
        "la": "?..."
    },

    "2": {
        "la": "..."
    },

    "3": {
        "page": 628,
        "la": "..."
    },

    "4": {
        "la": "..."
    },

    "5": {
        "la": "..."
    },

    "6": {
        "mark": "*",
        "la": "..."
    },

    "7": {
        "la": "..."
    },

    "8": {
        "mark": "*",
        "la": "..."
    },

    "9": {
        "mark": "*",
        "la": "..."
    },

    "10": {
        "la": "..."
    },

    "11": {
        "mark": "*",
        "la": "..."
    },

    "12": {
        "page": 628,
        "la": "Lincolniae in Anglia, sancti [1|Hugonis], episcopi, ..."
    },

    "13": {
        "mark": "*",
        "la": "Apud Cracoviam in Polonia, beatae [1|Salomeae] ..."
    },

    "14": {
        "la": "..."
    },

    "15": {
        "la": "..."
    },

    "16": {
        "la": "..."
    },

    "17": {
        "mark": "*",
        "la": "..."
    },

    "18": {
        "mark": "*",
        "la": "..."
    }
}
