{
    "names": {
        "la": [
            "Viginti Martyres persecutionis Diocletiani Nicomediae"
        ],
        "en": [
            "Twenty Martyrs of the Diocletianic persecution in Nicomedia"
        ],
        "pl": [
            "Dwudziestu Męczenników prześladowań Dioklecjana w Nikomedii"
        ]
    },
    "forenames": ["multa"],
    "surnames": null,
    "epithets": null,

    "active": true,

    "born": null,
    "died": ["~303"],
    "beatified": null,
    "canonized": null,
    "anniversary": null,

    "categories": ["socia", "martyr"],

    "data-links": {
        "mr-1584": ["1:Dec./23#2"],
        "mr-1584-movable": [],

        "mr-1956": ["1:Decembris/23#3"],
        "mr-1956-movable": [],

        "mr-2004": [],
        "mr-2004-movable": []
    },

    "sources": {
        "causesanti": null,
        "gcatholic": null,
        "wiki": "https://pl.wikipedia.org/wiki/M%C4%99czennicy_z_Nikomedii"
    }
}
