{
    "1": {
        "page": 127,
        "la": "In Phrygia, commemoratio sancti [1|Tryphonis], martyris."
    },

    "2": {
        "la": "..."
    },

    "3": {
        "la": "..."
    },

    "4": {
        "la": "..."
    },

    "5": {
        "mark": "*",
        "la": "..."
    },

    "6": {
        "mark": "*",
        "la": "..."
    },

    "7": {
        "mark": "*",
        "la": "..."
    },

    "8": {
        "mark": "*",
        "la": "..."
    },

    "9": {
        "page": 128,
        "mark": "*",
        "la": "..."
    },

    "10": {
        "mark": "*",
        "la": "..."
    },

    "11": {
        "mark": "*",
        "la": "..."
    },

    "12": {
        "mark": "*",
        "la": "..."
    },

    "13": {
        "mark": "*",
        "la": "..."
    },

    "14": {
        "la": "..."
    },

    "15": {
        "mark": "*",
        "la": "..."
    },

    "16": {
        "page": 129,
        "la": "..."
    },

    "17": {
        "mark": "*",
        "la": "..."
    },

    "18": {
        "mark": "*",
        "la": "..."
    }
}
