{
    "getBaptismOfJesusFeastDateValidToday|0": {
        "records/god/fil#bad": {
            "name": {
                "la": "Iesus Christus (Baptismus Domini)",
                "pl": "Jezus Chrystus (Chrzest Pański)"
            },
            "sources": {
                "mr-2004-movable": "#3"
            }
        }
    },
    "getFirstSundayOfAdventDateValidSince1956|-7": {
        "records/god/fil#rex": {
            "name": {
                "la": "Iesus Christus (Iesus Christus Universorum Rex)",
                "pl": "Jezus Chrystus (Jezus Chrystus Król Wszechświata)"
            },
            "sources": {
                "mr-2004-movable": "#15"
            }
        }
    },
    "getFirstSundayOfAdventDateValidSince1956|0": {
        "records/god/fil#d1a": {
            "name": {
                "la": "Iesus Christus (Dominica prima Adventus)",
                "pl": "Jezus Chrystus (Pierwsza Niedziela Adwentu)"
            },
            "sources": {
                "mr-1956-movable": "#1",
                "mr-2004-movable": "#1"
            }
        }
    },
    "getHolyFamilyFeastDateValidSince1956|0": {
        "records/god/fil#sfa": {
            "name": {
                "la": "Iesus Christus (Sancta Familia)",
                "pl": "Jezus Chrystus (Święta Rodzina)"
            },
            "sources": {
                "mr-1956-movable": "#3"
            }
        },
        "records/patrons/ioseph/naz#sfa": {
            "name": {
                "la": "Ioseph Nazarenus (Sancta Familia)",
                "pl": "Józef z Nazaretu (Święta Rodzina)"
            },
            "sources": {
                "mr-1956-movable": "#3"
            }
        }
    },
    "getHolyFamilyFeastDateValidSince1960|0": {
        "records/god/fil#sfa": {
            "name": {
                "la": "Iesus Christus (Sancta Familia)",
                "pl": "Jezus Chrystus (Święta Rodzina)"
            },
            "sources": {
                "mr-1956-movable-variations": "#3-ab-1960-07-26"
            }
        },
        "records/patrons/ioseph/naz#sfa": {
            "name": {
                "la": "Ioseph Nazarenus (Sancta Familia)",
                "pl": "Józef z Nazaretu (Święta Rodzina)"
            },
            "sources": {
                "mr-1956-movable-variations": "#3-ab-1960-07-26"
            }
        }
    },
    "getHolyFamilyFeastDateValidSince2001|0": {
        "records/god/fil#sfa": {
            "name": {
                "la": "Iesus Christus (Sancta Familia)",
                "pl": "Jezus Chrystus (Święta Rodzina)"
            },
            "sources": {
                "mr-2004-movable": "#2"
            }
        },
        "records/patrons/ioseph/naz#sfa": {
            "name": {
                "la": "Ioseph Nazarenus (Sancta Familia)",
                "pl": "Józef z Nazaretu (Święta Rodzina)"
            },
            "sources": {
                "mr-2004-movable": "#2"
            }
        }
    },
    "getJesusTheKingFeastDateValidSince1956|0": {
        "records/god/fil#rex": {
            "name": {
                "la": "Iesus Christus (Iesus Christus Universorum Rex)",
                "pl": "Jezus Chrystus (Jezus Chrystus Król Wszechświata)"
            },
            "sources": {
                "mr-1956-movable": "#25"
            }
        }
    },
    "getMissingDate|0": {
        "records/god/fil#aso": {
            "name": {
                "la": "Iesus Christus (Octava Ascensionis Iesu Christi)",
                "pl": "Jezus Chrystus (Oktawa Wniebowstąpienia Jezusa Chrystusa)"
            },
            "sources": {
                "mr-1956-movable-variations": "#17-ab-1960-07-26"
            }
        },
        "records/god/fil#cro": {
            "name": {
                "la": "Iesus Christus (Octava Sanctissimi Corporis Christi)",
                "pl": "Jezus Chrystus (Oktawa Najświętszego Ciała Chrystusa)"
            },
            "sources": {
                "mr-1956-movable-variations": "#22-ab-1960-07-26"
            }
        },
        "records/god/fil#sco": {
            "name": {
                "la": "Iesus Christus (Octava Sacratissimi Cordis Iesu)",
                "pl": "Jezus Chrystus (Oktawa Najświętszego Serca Jezusa)"
            },
            "sources": {
                "mr-1956-movable-variations": "#24-ab-1960-07-26"
            }
        }
    },
    "getResurrectionFeastDateValidSince1584OrEarlier|-1": {
        "records/god/fil#sas": {
            "name": {
                "la": "Iesus Christus (Sabbato sancto)",
                "pl": "Jezus Chrystus (Wielka Sobota)"
            },
            "sources": {
                "mr-2004-movable": "#7"
            }
        }
    },
    "getResurrectionFeastDateValidSince1584OrEarlier|-14": {
        "records/god/fil#dps": {
            "name": {
                "la": "Iesus Christus (Dominica Passionis)",
                "pl": "Jezus Chrystus (Niedziela Męki Pańskiej)"
            },
            "sources": {
                "mr-1956-movable": "#6",
                "mr-1956-movable-variations": "#6-ab-1960-07-26"
            }
        }
    },
    "getResurrectionFeastDateValidSince1584OrEarlier|-2": {
        "records/god/fil#f6p": {
            "name": {
                "la": "Iesus Christus (feria sexta in Passione Domini)",
                "pl": "Jezus Chrystus (Wielki Piątek)"
            },
            "sources": {
                "mr-2004-movable": "#7"
            }
        }
    },
    "getResurrectionFeastDateValidSince1584OrEarlier|-3": {
        "records/god/fil#f5h": {
            "name": {
                "la": "Iesus Christus (Feria quinta Hebdomadae sanctae)",
                "pl": "Jezus Chrystus (Wielki Czwartek)"
            },
            "sources": {
                "mr-1584-movable": "#4",
                "mr-1956-movable": "#9",
                "mr-2004-movable": "#7"
            }
        }
    },
    "getResurrectionFeastDateValidSince1584OrEarlier|-42": {
        "records/god/fil#d1q": {
            "name": {
                "la": "Iesus Christus (Dominica prima in Quadragesima)",
                "pl": "Jezus Chrystus (Pierwsza Niedziela Wielkiego Postu)"
            },
            "sources": {
                "mr-2004-movable": "#5"
            }
        }
    },
    "getResurrectionFeastDateValidSince1584OrEarlier|-46": {
        "records/god/fil#dci": {
            "name": {
                "en": "Jesus Christ (Ash Wednesday)",
                "la": "Iesus Christus (Dies Cinerum)",
                "pl": "Jezus Chrystus (Środa Popielcowa)"
            },
            "sources": {
                "mr-1584-movable": "#2",
                "mr-1956-movable": "#5",
                "mr-2004-movable": "#4"
            }
        }
    },
    "getResurrectionFeastDateValidSince1584OrEarlier|-63": {
        "records/god/fil#d70": {
            "name": {
                "la": "Iesus Christus (Dominica Septuagesimæ)",
                "pl": "Jezus Chrystus (Niedziela Siedemdziesiątnicy)"
            },
            "sources": {
                "mr-1584-movable": "#1",
                "mr-1956-movable": "#4"
            }
        }
    },
    "getResurrectionFeastDateValidSince1584OrEarlier|-7": {
        "records/god/fil#dpl": {
            "name": {
                "la": "Iesus Christus (Dominica in Palmis de Passione Domini)",
                "pl": "Jezus Chrystus (Niedziela Palmowa Męki Pańskiej)"
            },
            "sources": {
                "mr-1584-movable": "#3",
                "mr-1956-movable": "#8",
                "mr-1956-movable-variations": "#8-ab-1960-07-26",
                "mr-2004-movable": "#6"
            }
        }
    },
    "getResurrectionFeastDateValidSince1584OrEarlier|0": {
        "records/god/fil#res": {
            "name": {
                "la": "Iesus Christus (Resurrectio Iesu Christi)",
                "pl": "Jezus Chrystus (Zmartwychwstanie Jezusa Chrystusa)"
            },
            "sources": {
                "mr-1584-movable": "#5",
                "mr-1956-movable": "#10",
                "mr-2004-movable": "#8"
            }
        }
    },
    "getResurrectionFeastDateValidSince1584OrEarlier|37": {
        "records/god/fil#ril": {
            "name": {
                "la": "Iesus Christus (Romae Litaniae minores ad sanctum Joannem in Laterano)",
                "pl": "Jezus Chrystus (Rzymska mała procesja błagalna do świętego Jana na Lateranie)"
            },
            "sources": {
                "mr-1956-movable": "#14"
            }
        }
    },
    "getResurrectionFeastDateValidSince1584OrEarlier|38": {
        "records/god/fil#asv": {
            "name": {
                "la": "Iesus Christus (Vigilia Ascensionis Iesu Christi)",
                "pl": "Jezus Chrystus (Wigilia Wniebowstąpienia Jezusa Chrystusa)"
            },
            "sources": {
                "mr-1956-movable": "#15"
            }
        }
    },
    "getResurrectionFeastDateValidSince1584OrEarlier|39": {
        "records/god/fil#asc": {
            "name": {
                "la": "Iesus Christus (Ascénsio Iesu Christi)",
                "pl": "Jezus Chrystus (Wniebowstąpienie Jezusa Chrystusa)"
            },
            "sources": {
                "mr-1584-movable": "#6",
                "mr-1956-movable": "#16",
                "mr-2004-movable": "#9"
            }
        }
    },
    "getResurrectionFeastDateValidSince1584OrEarlier|42": {
        "records/god/fil#asc": {
            "name": {
                "la": "Iesus Christus (Ascénsio Iesu Christi)",
                "pl": "Jezus Chrystus (Wniebowstąpienie Jezusa Chrystusa)"
            },
            "sources": {
                "mr-2004-movable": "#9"
            }
        }
    },
    "getResurrectionFeastDateValidSince1584OrEarlier|46": {
        "records/god/fil#aso": {
            "name": {
                "la": "Iesus Christus (Octava Ascensionis Iesu Christi)",
                "pl": "Jezus Chrystus (Oktawa Wniebowstąpienia Jezusa Chrystusa)"
            },
            "sources": {
                "mr-1956-movable": "#17"
            }
        }
    },
    "getResurrectionFeastDateValidSince1584OrEarlier|48": {
        "records/god/spi#pev": {
            "name": {
                "la": "Spiritus Sanctus (Vigilia Pentecostes)",
                "pl": "Duch Święty (Wigilia Zesłania Ducha Świętego)"
            },
            "sources": {
                "mr-1956-movable": "#18"
            }
        }
    },
    "getResurrectionFeastDateValidSince1584OrEarlier|49": {
        "records/god/spi#pen": {
            "name": {
                "la": "Spiritus Sanctus (Dies Pentecostes)",
                "pl": "Duch Święty (Zesłanie Ducha Świętego)"
            },
            "sources": {
                "mr-1584-movable": "#7",
                "mr-1956-movable": "#19",
                "mr-2004-movable": "#10"
            }
        }
    },
    "getResurrectionFeastDateValidSince1584OrEarlier|56": {
        "records/god/tri#tri": {
            "name": {
                "la": "Sacratissima Trinitas (Sollemnitas sacratissimae et indivíduae Trinitatis)",
                "pl": "Trójca Przenajświętsza (Uroczystość Trójcy Przenajświętszej)"
            },
            "sources": {
                "mr-1584-movable": "#8",
                "mr-1956-movable": "#20",
                "mr-2004-movable": "#11"
            }
        },
        "records/god/spi#peo": {
            "name": {
                "la": "Spiritus Sanctus (Octava Pentecostes)",
                "pl": "Duch Święty (Oktawa Zesłania Ducha Świętego)"
            },
            "sources": {
                "mr-1956-movable": "#20"
            }
        }
    },
    "getResurrectionFeastDateValidSince1584OrEarlier|60": {
        "records/god/fil#ces": {
            "name": {
                "la": "Iesus Christus (Sanctissimum Corpore et Sanguis Christi)",
                "pl": "Jezus Chrystus (Najświętsze Ciało i Krew Chrystusa)"
            },
            "sources": {
                "mr-1584-movable": "#9",
                "mr-1956-movable": "#21",
                "mr-2004-movable": "#12"
            }
        }
    },
    "getResurrectionFeastDateValidSince1584OrEarlier|63": {
        "records/god/fil#ces": {
            "name": {
                "la": "Iesus Christus (Sanctissimum Corpore et Sanguis Christi)",
                "pl": "Jezus Chrystus (Najświętsze Ciało i Krew Chrystusa)"
            },
            "sources": {
                "mr-2004-movable": "#12"
            }
        }
    },
    "getResurrectionFeastDateValidSince1584OrEarlier|67": {
        "records/god/fil#cro": {
            "name": {
                "la": "Iesus Christus (Octava Sanctissimi Corporis Christi)",
                "pl": "Jezus Chrystus (Oktawa Najświętszego Ciała Chrystusa)"
            },
            "sources": {
                "mr-1956-movable": "#22"
            }
        }
    },
    "getResurrectionFeastDateValidSince1584OrEarlier|68": {
        "records/god/fil#sci": {
            "name": {
                "la": "Iesus Christus (Sanctissimum Cor Iesu)",
                "pl": "Jezus Chrystus (Najświętsze Serce Jezusa)"
            },
            "sources": {
                "mr-1956-movable": "#23",
                "mr-2004-movable": "#13"
            }
        }
    },
    "getResurrectionFeastDateValidSince1584OrEarlier|7": {
        "records/god/fil#dia": {
            "name": {
                "la": "Iesus Christus (Dominica in Albis)",
                "pl": "Jezus Chrystus (Niedziela Biała)"
            },
            "sources": {
                "mr-1956-movable": "#12"
            }
        }
    },
    "getResurrectionFeastDateValidSince1584OrEarlier|75": {
        "records/god/fil#sco": {
            "name": {
                "la": "Iesus Christus (Octava Sacratissimi Cordis Iesu)",
                "pl": "Jezus Chrystus (Oktawa Najświętszego Serca Jezusa)"
            },
            "sources": {
                "mr-1956-movable": "#24"
            }
        }
    },
    "getTheMostHolyNameOfJesusFeastDateValidSince1956|0": {
        "records/god/fil#sni": {
            "name": {
                "la": "Iesus Christus (Sanctissimum Nomen Iesus)",
                "pl": "Jezus Chrystus (Najświętsze Imię Jezus)"
            },
            "sources": {
                "mr-1956-movable": "#2"
            }
        }
    }
}