{
    "data-links": {
        "7": {
            "1": "records/patrons/abundius/lat",
            "2": "records/patrons/abundantius/abu",
            "3": "records/patrons/marcianus/abu",
            "4": "records/patrons/ioannes/abu"
        },
        "5": {
            "1": "records/patrons/caecilia/rom",
            "2": "records/patrons/valerianus/tib",
            "3": "records/patrons/tiburtius/val"
        },
        "1": {
            "1": "records/patrons/cornelius/1pp",
            "2": "records/patrons/cyprianus/car"
        },
        "4": {
            "1": "records/patrons/martinus/1pp"
        }
    }
}